{
    "instrumentation": "solo singing with chorus accompaniment", 
    "work_relations": [
        {
            "mbid": "c6e43ac6-4a18-42ab-bcc4-46e29360051e", 
            "title": "Ak\u015fam Oldu H\u00fcz\u00fcnlendim Ben Yine"
        }
    ], 
    "section_annotations": [
        {
            "melodicStructure": "", 
            "time": [
                0.26752, 
                62.393939
            ], 
            "time_unit": "sec", 
            "lyricStructure": "", 
            "name": "Taksim"
        }, 
        {
            "melodicStructure": "A1", 
            "time": [
                62.393939, 
                77.827796
            ], 
            "time_unit": "sec", 
            "lyricStructure": "A1", 
            "name": "Zemin"
        }, 
        {
            "melodicStructure": "A2", 
            "time": [
                77.827796, 
                92.685456
            ], 
            "time_unit": "sec", 
            "lyricStructure": "A1", 
            "name": "Zemin"
        }, 
        {
            "melodicStructure": "B1", 
            "time": [
                92.685456, 
                107.090389
            ], 
            "time_unit": "sec", 
            "lyricStructure": "B1", 
            "name": "Nakarat"
        }, 
        {
            "melodicStructure": "C1", 
            "time": [
                107.090389, 
                123.059286
            ], 
            "time_unit": "sec", 
            "lyricStructure": "B2", 
            "name": "Nakarat2"
        }, 
        {
            "melodicStructure": "D1", 
            "time": [
                123.059286, 
                138.451986
            ], 
            "time_unit": "sec", 
            "lyricStructure": "C1", 
            "name": "Meyan"
        }, 
        {
            "melodicStructure": "E1", 
            "time": [
                138.451986, 
                154.503198
            ], 
            "time_unit": "sec", 
            "lyricStructure": "C1", 
            "name": "Meyan2"
        }, 
        {
            "melodicStructure": "B1", 
            "time": [
                154.503198, 
                168.578875
            ], 
            "time_unit": "sec", 
            "lyricStructure": "B1", 
            "name": "Nakarat"
        }, 
        {
            "melodicStructure": "B2", 
            "time": [
                168.578875, 
                181.913728
            ], 
            "time_unit": "sec", 
            "lyricStructure": "B2", 
            "name": "Nakarat3"
        }
    ], 
    "symbTr": "ussak--sarki--duyek--aksam_oldu_huzunlendim--semahat_ozdenses", 
    "title": "Ak\u015fam Oldu H\u00fcz\u00fcnlendim"
}